hlvox/__init__.py
hlvox/__main__.py
hlvox/manager.py
hlvox/multi_voice.py
hlvox/single_voice.py
hlvox/voice.py
hlvox-0.16.2.dist-info/licenses/AUTHORS
hlvox-0.16.2.dist-info/METADATA
hlvox-0.16.2.dist-info/WHEEL
hlvox-0.16.2.dist-info/top_level.txt
hlvox-0.16.2.dist-info/RECORD
