Metadata-Version: 2.4
Name: hlvox
Version: 0.16.2
Summary: Pieces together voice files to form sentences
Author-email: Blair Hagen <bhagen55@gmail.com>
License: MIT
Project-URL: Homepage, https://gitlab.com/bhagen/hlvox
Classifier: Development Status :: 4 - Beta
Classifier: Operating System :: Microsoft :: Windows
Classifier: Operating System :: POSIX
Classifier: Programming Language :: Python :: 3.11
Requires-Python: >=3.11
License-File: AUTHORS
Requires-Dist: psycopg2-binary
Requires-Dist: pydub
Requires-Dist: sqlalchemy
Dynamic: license-file
